helpers_ai/__init__.py
helpers_ai/__main__.py
helpers_ai/annotator/__init__.py
helpers_ai/annotator/annotate.py
helpers_ai/annotator/image_convertor.py
helpers_ai/annotator/video_convertor.py
helpers_ai/dataset_convertors/__init__.py
helpers_ai/dataset_convertors/coco2voc.py
helpers_ai/dataset_convertors/coco2yolo.py
helpers_ai/dataset_convertors/jm2mmocr.py
helpers_ai/dataset_convertors/voc2coco.py
helpers_ai/dataset_convertors/voc2yolo.py
helpers_ai/dataset_convertors/yolo2coco.py
helpers_ai/dataset_convertors/yolo2voc.py
helpers_ai/losses.py
helpers_ai/main.py
helpers_ai/utils/__init__.py
helpers_ai/utils/jm2mm.py
helpers_ai/utils/util.py
helpers_ai/utils/validator.py
helpers_ai/utils/voc.py
helpers_ai-0.0.3.dist-info/entry_points.txt
helpers_ai-0.0.3.dist-info/LICENSE
helpers_ai-0.0.3.dist-info/METADATA
helpers_ai-0.0.3.dist-info/WHEEL
helpers_ai-0.0.3.dist-info/RECORD
